spatialAUC/__init__.py
spatialAUC/spatialAUC.py
spatialAUC-0.0.9.dist-info/LICENSE
spatialAUC-0.0.9.dist-info/METADATA
spatialAUC-0.0.9.dist-info/WHEEL
spatialAUC-0.0.9.dist-info/top_level.txt
spatialAUC-0.0.9.dist-info/RECORD
