Metadata-Version: 2.1
Name: spatialAUC
Version: 0.0.9
Summary: Python package for gene set enrichment in spatial transcriptomic data
Author: Bence Kover
Author-email: kover.bence@gmail.com
Keywords: spatial,transcriptomics,gsea,moransi,enrichment
Classifier: Development Status :: 1 - Planning
Classifier: Intended Audience :: Science/Research
Classifier: Programming Language :: Python :: 3
Classifier: Operating System :: MacOS :: MacOS X
License-File: LICENSE
Requires-Dist: gseapy
Requires-Dist: scanpy
Requires-Dist: squidpy
Requires-Dist: numba
Requires-Dist: tqdm
